[
  {
    "slug": "chick-fil-a-centre-pointe",
    "decision": "approved"
  },
  {
    "slug": "chick-fil-a-north-charleston-delivery",
    "decision": "approved"
  },
  {
    "slug": "chick-fil-a-the-citadel",
    "decision": "approved"
  },
  {
    "slug": "jimmy-johns-north-charleston",
    "decision": "approved"
  },
  {
    "slug": "jimmy-johns-westedge",
    "decision": "approved"
  },
  {
    "slug": "jimmy-johns-savannah-hwy",
    "decision": "approved"
  },
  {
    "slug": "jimmy-johns-mt-pleasant",
    "decision": "approved"
  },
  {
    "slug": "chipotle-north-charleston-1",
    "decision": "approved"
  },
  {
    "slug": "chipotle-north-charleston-2",
    "decision": "approved"
  },
  {
    "slug": "chipotle-charleston-area-3",
    "decision": "approved"
  },
  {
    "slug": "chipotle-king-street",
    "decision": "approved"
  },
  {
    "slug": "chipotle-savannah-hwy",
    "decision": "approved"
  },
  {
    "slug": "chipotle-ladson",
    "decision": "approved"
  },
  {
    "slug": "chipotle-goose-creek",
    "decision": "approved"
  },
  {
    "slug": "chipotle-mt-pleasant",
    "decision": "approved"
  },
  {
    "slug": "famularis-pizzeria-hanahan",
    "decision": "approved"
  },
  {
    "slug": "famularis-pizzeria-west-ashley",
    "decision": "approved"
  },
  {
    "slug": "famularis-pizzeria-cainhoy",
    "decision": "approved"
  },
  {
    "slug": "famularis-pizzeria-oakbrook",
    "decision": "approved"
  },
  {
    "slug": "fams-brewing-co",
    "decision": "approved"
  },
  {
    "slug": "famularis-pizzeria-cane-bay",
    "decision": "approved"
  },
  {
    "slug": "johnnys-garage",
    "decision": "approved"
  },
  {
    "slug": "santis-restaurante-mexicano-meeting-st",
    "decision": "approved"
  },
  {
    "slug": "santis-west-ashley",
    "decision": "approved"
  },
  {
    "slug": "santis-mount-pleasant",
    "decision": "approved"
  },
  {
    "slug": "benny-rinaldis",
    "decision": "approved"
  },
  {
    "slug": "jenis-splendid-ice-creams-king-st",
    "decision": "approved"
  },
  {
    "slug": "jenis-splendid-ice-creams-mt-pleasant",
    "decision": "approved"
  },
  {
    "slug": "madra-rua-irish-pub-park-circle",
    "decision": "approved"
  },
  {
    "slug": "madra-rua-irish-pub-summerville",
    "decision": "approved"
  },
  {
    "slug": "coast-brewing-company",
    "decision": "approved"
  }
]
